pptm/__init__.py
pptm/py.typed
pptm/salut.py
pptm-0.2.2.dist-info/WHEEL
pptm-0.2.2.dist-info/METADATA
pptm-0.2.2.dist-info/RECORD
