Metadata-Version: 2.1
Name: pptm
Version: 0.2.2
Summary: A short description of the project
Home-page: https://Michael-Cohen.github.io/ppt
License: Proprietary License
Author: Michael Cohen
Author-email: me@example.com
Requires-Python: >=3.9,<4.0
Classifier: Development Status :: 4 - Beta
Classifier: Intended Audience :: Developers
Classifier: License :: Other/Proprietary License
Classifier: Operating System :: OS Independent
Classifier: Programming Language :: Python
Classifier: Programming Language :: Python :: 3
Classifier: Programming Language :: Python :: 3.9
Classifier: Programming Language :: Python :: 3.10
Classifier: Programming Language :: Python :: 3.11
Classifier: Programming Language :: Python :: 3
Classifier: Programming Language :: Python :: 3.10
Classifier: Programming Language :: Python :: 3.9
Classifier: Topic :: Software Development :: Libraries :: Python Modules
Classifier: Typing :: Typed
Requires-Dist: numpy (>=1.22,<2.0)
Requires-Dist: python-semantic-release (>=7.33.2,<8.0.0)
Project-URL: Documentation, https://Michael-Cohen.github.io/ppt
Project-URL: Repository, https://github.com/Michael-Cohen/ppt
